setup.py
funniestv1/__init__.py
funniestv1.egg-info/PKG-INFO
funniestv1.egg-info/SOURCES.txt
funniestv1.egg-info/dependency_links.txt
funniestv1.egg-info/not-zip-safe
funniestv1.egg-info/top_level.txt