Metadata-Version: 1.0
Name: funniestv1
Version: 0.1
Summary: The funniest joke in the world
Home-page: http://github.com/storborg/funniest
Author: Flying Circus 1
Author-email: flyingcircus1@example.com
License: MIT
Platform: UNKNOWN
